graphab4py/__init__.py
graphab4py/functions.py
graphab4py/project.py
graphab4py-1.0.5.dist-info/LICENSE
graphab4py-1.0.5.dist-info/METADATA
graphab4py-1.0.5.dist-info/WHEEL
graphab4py-1.0.5.dist-info/top_level.txt
graphab4py-1.0.5.dist-info/RECORD
