Metadata-Version: 2.1
Name: graphab4py
Version: 1.0.5
Summary: A Python package to execute Graphab analyses.
Home-page: https://github.com/ManuelPopp/graphab4py
Author: Manuel R. Popp
Author-email: "Manuel R. Popp" <requests@cdpopp.de>
Project-URL: Homepage, https://github.com/manuelpopp/graphab4py
Project-URL: Issues, https://github.com/manuelpopp/graphab4py/issues
Keywords: Graphab,Network analysis
Classifier: Programming Language :: Python :: 3
Classifier: Development Status :: 4 - Beta
Classifier: License :: OSI Approved :: The Unlicense (Unlicense)
Classifier: Operating System :: OS Independent
Requires-Python: >=3.8
License-File: LICENSE
Requires-Dist: numpy
Requires-Dist: matplotlib
Requires-Dist: xmltodict
